Course_4/fifo/fifo.sv
module FIFO (
    input         clk,
    input         rst,
    input          wr,
    input          rd,
    input   [7:0] din,
    output [7:0] dout,
    output      empty,
    output       full
  );

  // Pointers for write and read operations
  reg [3:0] wptr = 0, rptr = 0;

  // Counter for tracking the number of elements in the FIFO
  reg [4:0] cnt = 0;

  // Memory array to store data
  reg [7:0] mem [15:0];

  reg [7:0] dout_t = 0;

  always @(posedge clk)
  begin
    if (rst == 1'b1)
    begin
      // Reset the pointers and counter when the reset signal is asserted
      wptr   <= 0;
      rptr   <= 0;
      cnt    <= 0;
      dout_t <= 0;
    end
    else if (wr && !full)
    begin
      // Write data to the FIFO if it's not full
      mem[wptr] <= din;
      wptr      <= wptr + 1;
      cnt       <= cnt + 1;
      dout_t    <= dout_t;
    end
    else if (rd && !empty)
    begin
      // Read data from the FIFO if it's not empty
      dout_t <= mem[rptr];
      rptr   <= rptr + 1;
      cnt    <= cnt - 1;
    end
  end

  // Determine if the FIFO is empty or full
  assign empty = (cnt == 0) ? 1'b1 : 1'b0;
  assign full  = (cnt == 16) ? 1'b1 : 1'b0;
  assign dout  = dout_t;

  initial
  begin
    $dumpfile("waveform_fifo.vcd");
    $dumpvars(1,FIFO);

  end

endmodule

Course_4/fifo/waveform_fifo.vcd
$date
	Sat Jan 24 10:27:39 2026
$end
$version
	Icarus Verilog
$end
$timescale
	1ps
$end
$scope module FIFO $end
$var wire 1 ! clk $end
$var wire 8 " din [7:0] $end
$var wire 8 # dout [7:0] $end
$var wire 1 $ rd $end
$var wire 1 % rst $end
$var wire 1 & wr $end
$var wire 1 ' full $end
$var wire 1 ( empty $end
$var reg 5 ) cnt [4:0] $end
$var reg 8 * dout_t [7:0] $end
$var reg 4 + rptr [3:0] $end
$var reg 4 , wptr [3:0] $end
$upscope $end
$enddefinitions $end
$comment Show the parameter values. $end
$dumpall
$end
#0
$dumpvars
b0 ,
b0 +
b0 *
b0 )
1(
0'
0&
1%
0$
b0 #
b0 "
1!
$end
#5000
0!
#10000
1!
#15000
0!
#20000
1!
#25000
0!
#30000
1!
#35000
0!
#40000
1&
b101 "
0%
1!
#45000
0!
#50000
0&
0(
b1 )
b1 ,
1!
#55000
0!
#60000
1&
b0 "
1!
#65000
0!
#70000
0&
b10 )
b10 ,
1!
#75000
0!
#80000
1&
b1110 "
1!
#85000
0!
#90000
0&
b11 )
b11 ,
1!
#95000
0!
#100000
1$
b1011 "
1!
#105000
0!
#110000
0$
b10 )
b1 +
b101 #
b101 *
1!
#115000
0!
#120000
1&
b1010 "
1!
#125000
0!
#130000
0&
b11 )
b100 ,
1!
#135000
0!
#140000
1$
b1001 "
1!
#145000
0!
#150000
0$
b10 )
b10 +
b0 #
b0 *
1!
#155000
0!
#160000
1$
b11 "
1!
#165000
0!
#170000
0$
b1 )
b11 +
b1110 #
b1110 *
1!
#175000
0!
#180000
1$
1!
#185000
0!
#190000
0$
1(
b0 )
b100 +
b1010 #
b1010 *
1!
#195000
0!
#200000
1&
b101 "
1!
#205000
0!
#210000
0&
0(
b1 )
b101 ,
1!
#215000
0!
#220000
1&
b11 "
1!
#225000
0!
#230000
0&
b10 )
b110 ,
1!
#235000
0!
#240000
1$
b1010 "
1!
#245000
0!
#250000
0$
b1 )
b101 +
b101 #
b101 *
1!
#255000
0!
#260000
1$
b0 "
1!
#265000
0!
#270000
0$
1(
b0 )
b110 +
b11 #
b11 *
1!
#275000
0!
#280000
1&
b101 "
1!
#285000
0!
#290000
0&
0(
b1 )
b111 ,
1!
#295000
0!
#300000
1&
1!
#305000
0!
#310000
0&
b10 )
b1000 ,
1!
#315000
0!
#320000
1$
b1111 "
1!
#325000
0!
#330000
0$
b1 )
b111 +
b101 #
b101 *
1!
#335000
0!
#340000
1$
b1110 "
1!
#345000
0!
#350000
0$
1(
b0 )
b1000 +
1!
#355000
0!
#360000
1&
b1000 "
1!
#365000
0!
#370000
0&
0(
b1 )
b1001 ,
1!
#375000
0!
#380000
1&
b1110 "
1!
#385000
0!
#390000
0&
b10 )
b1010 ,
1!
#395000
0!
#400000
1&
b1010 "
1!
#405000
0!
#410000
0&
b11 )
b1011 ,
1!
#415000
0!
#420000
1$
b0 "
1!
#425000
0!
#430000
0$
b10 )
b1001 +
b1000 #
b1000 *
1!
#435000
0!
#440000
1$
b1001 "
1!
#445000
0!
#450000
0$
b1 )
b1010 +
b1110 #
b1110 *
1!
#455000
0!
#460000
1$
b0 "
1!
#465000
0!
#470000
0$
1(
b0 )
b1011 +
b1010 #
b1010 *
1!
#475000
0!
#480000
1&
b1001 "
1!
#485000
0!
#490000
0&
0(
b1 )
b1100 ,
1!
#495000
0!
#500000
1$
b1101 "
1!
#505000
0!
#510000
0$
1(
b0 )
b1100 +
b1001 #
b1001 *
1!
#515000
0!
#520000
1&
b110 "
1!
#525000
0!
#530000
0&
0(
b1 )
b1101 ,
1!
#535000
0!
#540000
1$
b10 "
1!
#545000
0!
#550000
0$
1(
b0 )
b1101 +
b110 #
b110 *
1!
#555000
0!
#560000
1$
b1011 "
1!
#565000
0!
#570000
0$
1!
#575000
0!
#580000
1&
1!
#585000
0!
#590000
0&
0(
b1 )
b1110 ,
1!
#595000
0!
#600000
1$
b1010 "
1!
#605000
0!
#610000
0$
1(
b0 )
b1110 +
b1011 #
b1011 *
1!
#615000
0!
#620000
1$
b1100 "
1!
#625000
0!
#630000
0$
1!
#635000
0!
#640000
1&
b1011 "
1!
#645000
0!
#650000
0&
0(
b1 )
b1111 ,
1!
#655000
0!
#660000
1$
b0 "
1!
#665000
0!
#670000
0$
1(
b0 )
b1111 +
1!
#675000
0!
#680000
1$
b110 "
1!
#685000
0!
#690000
0$
1!
#695000
0!
#700000
1$
b1111 "
1!
#705000
0!
#710000
0$
1!
#715000
0!
#720000
1$
b10 "
1!
#725000
0!
#730000
0$
1!
#735000
0!
#740000
1&
b1101 "
1!
#745000
0!
#750000
0&
0(
b1 )
b0 ,
1!
#755000
0!
#760000
1$
b11 "
1!
#765000
0!
#770000
0$
1(
b0 )
b0 +
b1101 #
b1101 *
1!
#775000
0!
#780000
1$
b1 "
1!
#785000
0!
#790000
0$
1!
#795000
0!
#800000
1&
b1101 "
1!
#805000
0!
#810000
0&
0(
b1 )
b1 ,
1!
#815000
0!
#820000
1$
b1011 "
1!
#825000
0!
#830000
0$
1(
b0 )
b1 +
1!
