Course_2/pri_encoder/pri_enc.sv
module pri_enc(
  input en,
  input [7:0]i,
  output reg [2:0]y
  );
  
  always@(*)
  begin
    if(en==1)
      begin
        if(i[7]==1) y=3'b111;
        else if(i[6]==1) y=3'b110;
        else if(i[5]==1) y=3'b101;
        else if(i[4]==1) y=3'b100;
        else if(i[3]==1) y=3'b011;
        else if(i[2]==1) y=3'b010;
        else if(i[1]==1) y=3'b001;
        else if(i[0]==1) y=3'b000;
        else
        y=3'b000;
      end
    else y=3'b000;
  end
  
  
initial begin
$dumpfile("dump.vcd");
$dumpvars(1,pri_enc);
end



endmodule

Course_2/pri_encoder/dump.vcd
$date
	Wed Jan  7 13:29:35 2026
$end
$version
	Icarus Verilog
$end
$timescale
	1ps
$end
$scope module pri_enc $end
$var wire 1 ! en $end
$var wire 8 " i [7:0] $end
$var reg 3 # y [2:0] $end
$upscope $end
$enddefinitions $end
$comment Show the parameter values. $end
$dumpall
$end
#0
$dumpvars
b1 #
b11 "
1!
$end
#20000
b111 #
b11111111 "
#40000
b10010010 "
#60000
b110 #
b1010000 "
#80000
b111 #
b11110101 "
#100000
b11011010 "
#120000
b110 #
b1000010 "
#140000
b0 #
b0 "
#160000
b110 #
b1010011 "
#180000
b111 #
b10000000 "
#200000
b10010100 "
#220000
b11011110 "
#240000
b10010011 "
#260000
b110 #
b1000011 "
#280000
b111 #
b10010110 "
#300000
b110 #
b1110011 "
#320000
b100 #
b10111 "
#340000
b111 #
b10000010 "
#360000
b110 #
b1110010 "
#380000
b111 #
b11101011 "
#400000
b110 #
b1111101 "
#420000
b111 #
b11111011 "
#440000
b10101111 "
#460000
b10111011 "
#480000
b1 #
b10 "
#500000
b110 #
b1111101 "
#520000
b111 #
b10101001 "
#540000
b11000010 "
#560000
b101 #
b111010 "
#580000
b111 #
b10010000 "
