Course_4/d_flip_flop/dff.sv
module dff (
    input       clk,
    input       rst,
    input       din,
    output reg  dout
  );

  always@(posedge clk)
  begin
    if(rst == 1'b1)
      dout <= 1'b0;
    else
      dout <= din;
  end


  initial
  begin
    $dumpfile("dump.vcd");
    $dumpvars(1, dff);
  end


endmodule

Course_4/d_flip_flop/dump.vcd
$date
	Sat Jan 24 01:37:55 2026
$end
$version
	Icarus Verilog
$end
$timescale
	1ps
$end
$scope module dff $end
$var wire 1 ! clk $end
$var wire 1 " din $end
$var wire 1 # rst $end
$var reg 1 $ dout $end
$upscope $end
$enddefinitions $end
$comment Show the parameter values. $end
$dumpall
$end
#0
$dumpvars
0$
1#
0"
1!
$end
#5000
0!
#10000
1!
#15000
0!
#20000
1!
#25000
0!
#30000
1!
#35000
0!
#40000
1"
0#
1!
#45000
0!
#50000
0"
1$
1!
#55000
0!
#60000
1"
0$
1!
#65000
0!
#70000
0"
1$
1!
#75000
0!
#80000
0$
1!
#85000
0!
#90000
1!
#95000
0!
#100000
1"
1!
#105000
0!
#110000
0"
1$
1!
#115000
0!
#120000
0$
1!
#125000
0!
#130000
1!
#135000
0!
#140000
1!
#145000
0!
#150000
1!
#155000
0!
#160000
1"
1!
#165000
0!
#170000
0"
1$
1!
#175000
0!
#180000
1"
0$
1!
#185000
0!
#190000
0"
1$
1!
#195000
0!
#200000
0$
1!
#205000
0!
#210000
1!
#215000
0!
#220000
1"
1!
#225000
0!
#230000
0"
1$
1!
